{"f1_score": 0.026566180930750884, "tfidf": false, "recall": 0.11330049261083744, "n_neighbors": 10, "test": 100, "metric": "cosine", "precision": 0.14526421854008062, "smoothing": 0.001, "expansion_threshold": null, "weighting": "milne", "train": 5, "stemming": "porter", "classify_method": "multilabel", "KBest": 3000, "expansion_relatedness": null, "threshold": 0.01, "representation": "BoW", "corpus": "oercommons", "accuracy": 0.12, "expanded_weighting": null, "hamming_loss": 0.11666666666666667}