{"metric": "cosine", "weighting": "milne", "threshold": 0.01, "expansion_threshold": null, "smoothing": 0.001, "stemming": "porter", "classify_method": "multilabel", "test": 1000, "KBest": 3000, "corpus": "merlot", "accuracy": 0.121, "f1_score": 0.053973314031503503, "precision": 0.1827405748577392, "train": 5, "expansion_relatedness": null, "expanded_weighting": null, "n_neighbors": 10, "algorithm": "SGD", "recall": 0.12396694214876033, "tfidf": false, "representation": "BoW", "hamming_loss": 0.19966666666666666}