{"metric": "cosine", "weighting": "milne", "threshold": 0.01, "expansion_threshold": null, "smoothing": 0.001, "stemming": "porter", "classify_method": "multilabel", "test": 500, "KBest": 3000, "corpus": "oercommons", "accuracy": 0.062, "f1_score": 0.02145892712903022, "precision": 0.09903002942898867, "train": 10, "expansion_relatedness": null, "expanded_weighting": null, "n_neighbors": 10, "algorithm": "linear_SVC", "recall": 0.033824804856895055, "tfidf": false, "representation": "BoW", "hamming_loss": 0.12095238095238095}